[
    {
        "id": "kbDRi4G2",
        "createdBy": "lichess",
        "system": "arena",
        "minutes": 480,
        "clock": {
            "limit": 600,
            "increment": 0
        },
        "rated": true,
        "fullName": "Rapid Shield Arena",
        "nbPlayers": 430,
        "variant": {
            "key": "standard",
            "short": "Std",
            "name": "Standard"
        },
        "startsAt": 1781193600000,
        "finishesAt": 1781222400000,
        "status": 10,
        "perf": {
            "key": "rapid",
            "name": "Rapid",
            "position": 2,
            "icon": "#"
        },
        "secondsToStart": 971,
        "minRatedGames": {
            "nb": 15
        },
        "schedule": {
            "freq": "shield",
            "speed": "rapid"
        }
    },
    {
        "id": "oxM952rG",
        "createdBy": "lichess",
        "system": "arena",
        "minutes": 57,
        "clock": {
            "limit": 60,
            "increment": 2
        },
        "rated": true,
        "fullName": "Hourly Atomic Arena",
        "nbPlayers": 3,
        "variant": {
            "key": "atomic",
            "short": "Atom",
            "name": "Atomic"
        },
        "startsAt": 1781193602500,
        "finishesAt": 1781197022500,
        "status": 10,
        "perf": {
            "key": "atomic",
            "name": "Atomic",
            "position": 10
        },
        "secondsToStart": 973,
        "schedule": {
            "freq": "hourly",
            "speed": "superBlitz"
        }
    },
    {
        "id": "dyE9HmJz",
        "createdBy": "lichess",
        "system": "arena",
        "minutes": 27,
        "clock": {
            "limit": 30,
            "increment": 0
        },
        "rated": true,
        "fullName": "Hourly HyperBullet Arena",
        "nbPlayers": 0,
        "variant": {
            "key": "standard",
            "short": "Std",
            "name": "Standard"
        },
        "startsAt": 1781193605000,
        "finishesAt": 1781195225000,
        "status": 10,
        "perf": {
            "key": "bullet",
            "name": "Bullet",
            "position": 0,
            "icon": "T"
        },
        "secondsToStart": 976,
        "minRatedGames": {
            "nb": 20
        },
        "schedule": {
            "freq": "hourly",
            "speed": "hyperBullet"
        }
    },
    {
        "id": "x6sfrEEU",
        "createdBy": "lichess",
        "system": "arena",
        "minutes": 57,
        "clock": {
            "limit": 180,
            "increment": 0
        },
        "rated": true,
        "fullName": "Hourly Crazyhouse Arena",
        "nbPlayers": 0,
        "variant": {
            "key": "crazyhouse",
            "short": "Crazy",
            "name": "Crazyhouse"
        },
        "startsAt": 1781193607500,
        "finishesAt": 1781197027500,
        "status": 10,
        "perf": {
            "key": "crazyhouse",
            "name": "Crazyhouse",
            "position": 5
        },
        "secondsToStart": 978,
        "schedule": {
            "freq": "hourly",
            "speed": "superBlitz"
        }
    },
    {
        "id": "9rZ1pbqE",
        "createdBy": "lichess",
        "system": "arena",
        "minutes": 57,
        "clock": {
            "limit": 300,
            "increment": 0
        },
        "rated": true,
        "fullName": "≤1700 Blitz Arena",
        "nbPlayers": 2,
        "variant": {
            "key": "standard",
            "short": "Std",
            "name": "Standard"
        },
        "startsAt": 1781193610000,
        "finishesAt": 1781197030000,
        "status": 10,
        "perf": {
            "key": "blitz",
            "name": "Blitz",
            "position": 1,
            "icon": ")"
        },
        "secondsToStart": 981,
        "hasMaxRating": true,
        "maxRating": {
            "rating": 1700
        },
        "minRatedGames": {
            "nb": 20
        },
        "schedule": {
            "freq": "hourly",
            "speed": "blitz"
        }
    },
    {
        "id": "w6ZC7BYW",
        "createdBy": "lichess",
        "system": "arena",
        "minutes": 57,
        "clock": {
            "limit": 180,
            "increment": 0
        },
        "rated": true,
        "fullName": "Hourly King of the Hill Arena",
        "nbPlayers": 0,
        "variant": {
            "key": "kingOfTheHill",
            "short": "KotH",
            "name": "King of the Hill"
        },
        "startsAt": 1781193612500,
        "finishesAt": 1781197032500,
        "status": 10,
        "perf": {
            "key": "kingOfTheHill",
            "name": "King of the Hill",
            "position": 7
        },
        "secondsToStart": 983,
        "schedule": {
            "freq": "hourly",
            "speed": "superBlitz"
        }
    },
    {
        "id": "CYim6EqJ",
        "createdBy": "lichess",
        "system": "arena",
        "minutes": 57,
        "clock": {
            "limit": 180,
            "increment": 0
        },
        "rated": true,
        "fullName": "Hourly SuperBlitz Arena",
        "nbPlayers": 4,
        "variant": {
            "key": "standard",
            "short": "Std",
            "name": "Standard"
        },
        "startsAt": 1781193615000,
        "finishesAt": 1781197035000,
        "status": 10,
        "perf": {
            "key": "blitz",
            "name": "Blitz",
            "position": 1,
            "icon": ")"
        },
        "secondsToStart": 986,
        "minRatedGames": {
            "nb": 15
        },
        "schedule": {
            "freq": "hourly",
            "speed": "superBlitz"
        }
    },
    {
        "id": "lJcrvhjD",
        "createdBy": "lichess",
        "system": "arena",
        "minutes": 57,
        "clock": {
            "limit": 180,
            "increment": 0
        },
        "rated": true,
        "fullName": "Hourly Chess960 Arena",
        "nbPlayers": 0,
        "variant": {
            "key": "chess960",
            "short": "960",
            "name": "Chess960"
        },
        "startsAt": 1781193617500,
        "finishesAt": 1781197037500,
        "status": 10,
        "perf": {
            "key": "chess960",
            "name": "Chess960",
            "position": 6
        },
        "secondsToStart": 988,
        "schedule": {
            "freq": "hourly",
            "speed": "superBlitz"
        }
    },
    {
        "id": "4J1AmCaj",
        "createdBy": "lichess",
        "system": "arena",
        "minutes": 57,
        "clock": {
            "limit": 180,
            "increment": 0
        },
        "rated": true,
        "fullName": "≤2000 SuperBlitz Arena",
        "nbPlayers": 5,
        "variant": {
            "key": "standard",
            "short": "Std",
            "name": "Standard"
        },
        "startsAt": 1781193620000,
        "finishesAt": 1781197040000,
        "status": 10,
        "perf": {
            "key": "blitz",
            "name": "Blitz",
            "position": 1,
            "icon": ")"
        },
        "secondsToStart": 991,
        "hasMaxRating": true,
        "maxRating": {
            "rating": 2000
        },
        "minRatedGames": {
            "nb": 20
        },
        "schedule": {
            "freq": "hourly",
            "speed": "superBlitz"
        }
    },
    {
        "id": "wMGt2QAu",
        "createdBy": "lichess",
        "system": "arena",
        "minutes": 57,
        "clock": {
            "limit": 180,
            "increment": 2
        },
        "rated": true,
        "fullName": "Hourly Horde Arena",
        "nbPlayers": 3,
        "variant": {
            "key": "horde",
            "short": "Horde",
            "name": "Horde"
        },
        "startsAt": 1781193622500,
        "finishesAt": 1781197042500,
        "status": 10,
        "perf": {
            "key": "horde",
            "name": "Horde",
            "position": 11
        },
        "secondsToStart": 993,
        "schedule": {
            "freq": "hourly",
            "speed": "blitz"
        }
    },
    {
        "id": "pO4nGWjh",
        "createdBy": "lichess",
        "system": "arena",
        "minutes": 57,
        "clock": {
            "limit": 300,
            "increment": 0
        },
        "rated": true,
        "fullName": "Hourly Blitz Arena",
        "nbPlayers": 3,
        "variant": {
            "key": "standard",
            "short": "Std",
            "name": "Standard"
        },
        "startsAt": 1781193625000,
        "finishesAt": 1781197045000,
        "status": 10,
        "perf": {
            "key": "blitz",
            "name": "Blitz",
            "position": 1,
            "icon": ")"
        },
        "secondsToStart": 996,
        "minRatedGames": {
            "nb": 15
        },
        "schedule": {
            "freq": "hourly",
            "speed": "blitz"
        }
    },
    {
        "id": "Wnr7JcJR",
        "createdBy": "lichess",
        "system": "arena",
        "minutes": 57,
        "clock": {
            "limit": 600,
            "increment": 0
        },
        "rated": true,
        "fullName": "≤1500 Rapid Arena",
        "nbPlayers": 15,
        "variant": {
            "key": "standard",
            "short": "Std",
            "name": "Standard"
        },
        "startsAt": 1781193630000,
        "finishesAt": 1781197050000,
        "status": 10,
        "perf": {
            "key": "rapid",
            "name": "Rapid",
            "position": 2,
            "icon": "#"
        },
        "secondsToStart": 1001,
        "hasMaxRating": true,
        "maxRating": {
            "rating": 1500
        },
        "minRatedGames": {
            "nb": 20
        },
        "schedule": {
            "freq": "hourly",
            "speed": "rapid"
        }
    },
    {
        "id": "Hy2jm3z5",
        "createdBy": "lichess",
        "system": "arena",
        "minutes": 27,
        "clock": {
            "limit": 60,
            "increment": 0
        },
        "rated": true,
        "fullName": "≤1300 Bullet Arena",
        "nbPlayers": 2,
        "variant": {
            "key": "standard",
            "short": "Std",
            "name": "Standard"
        },
        "startsAt": 1781193635000,
        "finishesAt": 1781195255000,
        "status": 10,
        "perf": {
            "key": "bullet",
            "name": "Bullet",
            "position": 0,
            "icon": "T"
        },
        "secondsToStart": 1006,
        "hasMaxRating": true,
        "maxRating": {
            "rating": 1300
        },
        "minRatedGames": {
            "nb": 20
        },
        "schedule": {
            "freq": "hourly",
            "speed": "bullet"
        }
    },
    {
        "id": "vwwoYGW1",
        "createdBy": "lichess",
        "system": "arena",
        "minutes": 60,
        "clock": {
            "limit": 60,
            "increment": 0
        },
        "rated": true,
        "fullName": "Daily Bullet Arena",
        "nbPlayers": 13,
        "variant": {
            "key": "standard",
            "short": "Std",
            "name": "Standard"
        },
        "startsAt": 1781193640000,
        "finishesAt": 1781197240000,
        "status": 10,
        "perf": {
            "key": "bullet",
            "name": "Bullet",
            "position": 0,
            "icon": "T"
        },
        "secondsToStart": 1011,
        "minRatedGames": {
            "nb": 20
        },
        "schedule": {
            "freq": "daily",
            "speed": "bullet"
        }
    },
    {
        "id": "esAi72Pn",
        "createdBy": "lichess",
        "system": "arena",
        "minutes": 27,
        "clock": {
            "limit": 15,
            "increment": 0
        },
        "rated": true,
        "fullName": "Hourly UltraBullet Arena",
        "nbPlayers": 1,
        "variant": {
            "key": "standard",
            "short": "Std",
            "name": "Standard"
        },
        "startsAt": 1781195400000,
        "finishesAt": 1781197020000,
        "status": 10,
        "perf": {
            "key": "ultraBullet",
            "name": "UltraBullet",
            "position": 4,
            "icon": "{"
        },
        "secondsToStart": 2771,
        "schedule": {
            "freq": "hourly",
            "speed": "ultraBullet"
        }
    },
    {
        "id": "JzWFCYJ4",
        "createdBy": "lichess",
        "system": "arena",
        "minutes": 27,
        "clock": {
            "limit": 60,
            "increment": 1
        },
        "rated": true,
        "fullName": "≤1300 Bullet Arena",
        "nbPlayers": 0,
        "variant": {
            "key": "standard",
            "short": "Std",
            "name": "Standard"
        },
        "startsAt": 1781195440000,
        "finishesAt": 1781197060000,
        "status": 10,
        "perf": {
            "key": "bullet",
            "name": "Bullet",
            "position": 0,
            "icon": "T"
        },
        "secondsToStart": 2811,
        "hasMaxRating": true,
        "maxRating": {
            "rating": 1300
        },
        "minRatedGames": {
            "nb": 20
        },
        "schedule": {
            "freq": "hourly",
            "speed": "bullet"
        }
    },
    {
        "id": "PkYraNNc",
        "createdBy": "lichess",
        "system": "arena",
        "minutes": 90,
        "clock": {
            "limit": 180,
            "increment": 0
        },
        "rated": true,
        "fullName": "Daily SuperBlitz Arena",
        "nbPlayers": 0,
        "variant": {
            "key": "standard",
            "short": "Std",
            "name": "Standard"
        },
        "startsAt": 1781197200000,
        "finishesAt": 1781202600000,
        "status": 10,
        "perf": {
            "key": "blitz",
            "name": "Blitz",
            "position": 1,
            "icon": ")"
        },
        "secondsToStart": 4571,
        "minRatedGames": {
            "nb": 15
        },
        "schedule": {
            "freq": "daily",
            "speed": "superBlitz"
        }
    },
    {
        "id": "yUyEh0h5",
        "createdBy": "lichess",
        "system": "arena",
        "minutes": 57,
        "clock": {
            "limit": 180,
            "increment": 2
        },
        "rated": true,
        "fullName": "Hourly Atomic Arena",
        "nbPlayers": 1,
        "variant": {
            "key": "atomic",
            "short": "Atom",
            "name": "Atomic"
        },
        "startsAt": 1781197202500,
        "finishesAt": 1781200622500,
        "status": 10,
        "perf": {
            "key": "atomic",
            "name": "Atomic",
            "position": 10
        },
        "secondsToStart": 4573,
        "schedule": {
            "freq": "hourly",
            "speed": "blitz"
        }
    },
    {
        "id": "yC502SbC",
        "createdBy": "lichess",
        "system": "arena",
        "minutes": 27,
        "clock": {
            "limit": 60,
            "increment": 0
        },
        "rated": true,
        "fullName": "Hourly Bullet Arena",
        "nbPlayers": 0,
        "variant": {
            "key": "standard",
            "short": "Std",
            "name": "Standard"
        },
        "startsAt": 1781197205000,
        "finishesAt": 1781198825000,
        "status": 10,
        "perf": {
            "key": "bullet",
            "name": "Bullet",
            "position": 0,
            "icon": "T"
        },
        "secondsToStart": 4576,
        "minRatedGames": {
            "nb": 20
        },
        "schedule": {
            "freq": "hourly",
            "speed": "bullet"
        }
    },
    {
        "id": "6gGxmm8J",
        "createdBy": "lichess",
        "system": "arena",
        "minutes": 27,
        "clock": {
            "limit": 60,
            "increment": 0
        },
        "rated": true,
        "fullName": "Hourly Three-check Arena",
        "nbPlayers": 0,
        "variant": {
            "key": "threeCheck",
            "short": "3check",
            "name": "Three-check"
        },
        "startsAt": 1781197207500,
        "finishesAt": 1781198827500,
        "status": 10,
        "perf": {
            "key": "threeCheck",
            "name": "Three-Check",
            "position": 8
        },
        "secondsToStart": 4578,
        "schedule": {
            "freq": "hourly",
            "speed": "bullet"
        }
    },
    {
        "id": "Yb6T1Xmq",
        "createdBy": "lichess",
        "system": "arena",
        "minutes": 27,
        "clock": {
            "limit": 60,
            "increment": 0
        },
        "rated": true,
        "fullName": "≤1500 Bullet Arena",
        "nbPlayers": 0,
        "variant": {
            "key": "standard",
            "short": "Std",
            "name": "Standard"
        },
        "startsAt": 1781197210000,
        "finishesAt": 1781198830000,
        "status": 10,
        "perf": {
            "key": "bullet",
            "name": "Bullet",
            "position": 0,
            "icon": "T"
        },
        "secondsToStart": 4581,
        "hasMaxRating": true,
        "maxRating": {
            "rating": 1500
        },
        "minRatedGames": {
            "nb": 20
        },
        "schedule": {
            "freq": "hourly",
            "speed": "bullet"
        }
    },
    {
        "id": "egOhKRST",
        "createdBy": "lichess",
        "system": "arena",
        "minutes": 57,
        "clock": {
            "limit": 300,
            "increment": 3
        },
        "rated": true,
        "fullName": "Hourly Chess960 Arena",
        "nbPlayers": 1,
        "variant": {
            "key": "chess960",
            "short": "960",
            "name": "Chess960"
        },
        "startsAt": 1781197212500,
        "finishesAt": 1781200632500,
        "status": 10,
        "perf": {
            "key": "chess960",
            "name": "Chess960",
            "position": 6
        },
        "secondsToStart": 4583,
        "schedule": {
            "freq": "hourly",
            "speed": "blitz"
        }
    },
    {
        "id": "LvMnJSMc",
        "createdBy": "lichess",
        "system": "arena",
        "minutes": 57,
        "clock": {
            "limit": 300,
            "increment": 0
        },
        "rated": true,
        "fullName": "Hourly Blitz Arena",
        "nbPlayers": 0,
        "variant": {
            "key": "standard",
            "short": "Std",
            "name": "Standard"
        },
        "startsAt": 1781197215000,
        "finishesAt": 1781200635000,
        "status": 10,
        "perf": {
            "key": "blitz",
            "name": "Blitz",
            "position": 1,
            "icon": ")"
        },
        "secondsToStart": 4586,
        "minRatedGames": {
            "nb": 15
        },
        "schedule": {
            "freq": "hourly",
            "speed": "blitz"
        }
    },
    {
        "id": "tcCvwlpa",
        "createdBy": "lichess",
        "system": "arena",
        "minutes": 57,
        "clock": {
            "limit": 60,
            "increment": 2
        },
        "rated": true,
        "fullName": "Hourly Racing Kings Arena",
        "nbPlayers": 0,
        "variant": {
            "key": "racingKings",
            "short": "Racing",
            "name": "Racing Kings"
        },
        "startsAt": 1781197217500,
        "finishesAt": 1781200637500,
        "status": 10,
        "perf": {
            "key": "racingKings",
            "name": "Racing Kings",
            "position": 12
        },
        "secondsToStart": 4588,
        "schedule": {
            "freq": "hourly",
            "speed": "superBlitz"
        }
    },
    {
        "id": "H3sXVDk0",
        "createdBy": "lichess",
        "system": "arena",
        "minutes": 57,
        "clock": {
            "limit": 600,
            "increment": 0
        },
        "rated": true,
        "fullName": "≤1700 Rapid Arena",
        "nbPlayers": 3,
        "variant": {
            "key": "standard",
            "short": "Std",
            "name": "Standard"
        },
        "startsAt": 1781197220000,
        "finishesAt": 1781200640000,
        "status": 10,
        "perf": {
            "key": "rapid",
            "name": "Rapid",
            "position": 2,
            "icon": "#"
        },
        "secondsToStart": 4591,
        "hasMaxRating": true,
        "maxRating": {
            "rating": 1700
        },
        "minRatedGames": {
            "nb": 20
        },
        "schedule": {
            "freq": "hourly",
            "speed": "rapid"
        }
    },
    {
        "id": "wDryt3rj",
        "createdBy": "lichess",
        "system": "arena",
        "minutes": 57,
        "clock": {
            "limit": 180,
            "increment": 0
        },
        "rated": true,
        "fullName": "≤1300 SuperBlitz Arena",
        "nbPlayers": 0,
        "variant": {
            "key": "standard",
            "short": "Std",
            "name": "Standard"
        },
        "startsAt": 1781197225000,
        "finishesAt": 1781200645000,
        "status": 10,
        "perf": {
            "key": "blitz",
            "name": "Blitz",
            "position": 1,
            "icon": ")"
        },
        "secondsToStart": 4596,
        "hasMaxRating": true,
        "maxRating": {
            "rating": 1300
        },
        "minRatedGames": {
            "nb": 20
        },
        "schedule": {
            "freq": "hourly",
            "speed": "superBlitz"
        }
    },
    {
        "id": "DYnRNFrH",
        "createdBy": "lichess",
        "system": "arena",
        "minutes": 27,
        "clock": {
            "limit": 30,
            "increment": 0
        },
        "rated": true,
        "fullName": "Hourly HyperBullet Arena",
        "nbPlayers": 0,
        "variant": {
            "key": "standard",
            "short": "Std",
            "name": "Standard"
        },
        "startsAt": 1781197230000,
        "finishesAt": 1781198850000,
        "status": 10,
        "perf": {
            "key": "bullet",
            "name": "Bullet",
            "position": 0,
            "icon": "T"
        },
        "secondsToStart": 4601,
        "minRatedGames": {
            "nb": 20
        },
        "schedule": {
            "freq": "hourly",
            "speed": "hyperBullet"
        }
    },
    {
        "id": "1kUf43aJ",
        "createdBy": "lichess",
        "system": "arena",
        "minutes": 57,
        "clock": {
            "limit": 180,
            "increment": 2
        },
        "rated": true,
        "fullName": "Hourly Antichess Arena",
        "nbPlayers": 0,
        "variant": {
            "key": "antichess",
            "short": "Anti",
            "name": "Antichess"
        },
        "startsAt": 1781197235000,
        "finishesAt": 1781200655000,
        "status": 10,
        "perf": {
            "key": "antichess",
            "name": "Antichess",
            "position": 9
        },
        "secondsToStart": 4606,
        "schedule": {
            "freq": "hourly",
            "speed": "blitz"
        }
    },
    {
        "id": "zArtpBCc",
        "createdBy": "lichess",
        "system": "arena",
        "minutes": 57,
        "clock": {
            "limit": 300,
            "increment": 0
        },
        "rated": true,
        "fullName": "≤2000 Blitz Arena",
        "nbPlayers": 0,
        "variant": {
            "key": "standard",
            "short": "Std",
            "name": "Standard"
        },
        "startsAt": 1781197240000,
        "finishesAt": 1781200660000,
        "status": 10,
        "perf": {
            "key": "blitz",
            "name": "Blitz",
            "position": 1,
            "icon": ")"
        },
        "secondsToStart": 4611,
        "hasMaxRating": true,
        "maxRating": {
            "rating": 2000
        },
        "minRatedGames": {
            "nb": 20
        },
        "schedule": {
            "freq": "hourly",
            "speed": "blitz"
        }
    },
    {
        "id": "6eG9pVJE",
        "createdBy": "lichess",
        "system": "arena",
        "minutes": 27,
        "clock": {
            "limit": 60,
            "increment": 1
        },
        "rated": true,
        "fullName": "≤1500 Bullet Arena",
        "nbPlayers": 0,
        "variant": {
            "key": "standard",
            "short": "Std",
            "name": "Standard"
        },
        "startsAt": 1781199000000,
        "finishesAt": 1781200620000,
        "status": 10,
        "perf": {
            "key": "bullet",
            "name": "Bullet",
            "position": 0,
            "icon": "T"
        },
        "secondsToStart": 6371,
        "hasMaxRating": true,
        "maxRating": {
            "rating": 1500
        },
        "minRatedGames": {
            "nb": 20
        },
        "schedule": {
            "freq": "hourly",
            "speed": "bullet"
        }
    },
    {
        "id": "NssUzh78",
        "createdBy": "lichess",
        "system": "arena",
        "minutes": 27,
        "clock": {
            "limit": 30,
            "increment": 0
        },
        "rated": true,
        "fullName": "Hourly Three-check Arena",
        "nbPlayers": 1,
        "variant": {
            "key": "threeCheck",
            "short": "3check",
            "name": "Three-check"
        },
        "startsAt": 1781199010000,
        "finishesAt": 1781200630000,
        "status": 10,
        "perf": {
            "key": "threeCheck",
            "name": "Three-Check",
            "position": 8
        },
        "secondsToStart": 6381,
        "schedule": {
            "freq": "hourly",
            "speed": "hyperBullet"
        }
    },
    {
        "id": "3uDBR1VK",
        "createdBy": "lichess",
        "system": "arena",
        "minutes": 27,
        "clock": {
            "limit": 60,
            "increment": 0
        },
        "rated": true,
        "fullName": "Hourly Bullet Arena",
        "nbPlayers": 0,
        "variant": {
            "key": "standard",
            "short": "Std",
            "name": "Standard"
        },
        "startsAt": 1781199020000,
        "finishesAt": 1781200640000,
        "status": 10,
        "perf": {
            "key": "bullet",
            "name": "Bullet",
            "position": 0,
            "icon": "T"
        },
        "secondsToStart": 6391,
        "minRatedGames": {
            "nb": 20
        },
        "schedule": {
            "freq": "hourly",
            "speed": "bullet"
        }
    },
    {
        "id": "RtVkYTRV",
        "createdBy": "lichess",
        "system": "arena",
        "minutes": 27,
        "clock": {
            "limit": 15,
            "increment": 0
        },
        "rated": true,
        "fullName": "Hourly UltraBullet Arena",
        "nbPlayers": 1,
        "variant": {
            "key": "standard",
            "short": "Std",
            "name": "Standard"
        },
        "startsAt": 1781199040000,
        "finishesAt": 1781200660000,
        "status": 10,
        "perf": {
            "key": "ultraBullet",
            "name": "UltraBullet",
            "position": 4,
            "icon": "{"
        },
        "secondsToStart": 6411,
        "schedule": {
            "freq": "hourly",
            "speed": "ultraBullet"
        }
    },
    {
        "id": "NCBcvtDC",
        "createdBy": "lichess",
        "system": "arena",
        "minutes": 120,
        "clock": {
            "limit": 300,
            "increment": 0
        },
        "rated": true,
        "fullName": "Daily Blitz Arena",
        "nbPlayers": 0,
        "variant": {
            "key": "standard",
            "short": "Std",
            "name": "Standard"
        },
        "startsAt": 1781200800000,
        "finishesAt": 1781208000000,
        "status": 10,
        "perf": {
            "key": "blitz",
            "name": "Blitz",
            "position": 1,
            "icon": ")"
        },
        "secondsToStart": 8171,
        "minRatedGames": {
            "nb": 15
        },
        "schedule": {
            "freq": "daily",
            "speed": "blitz"
        }
    },
    {
        "id": "hrDqiYqM",
        "createdBy": "lichess",
        "system": "arena",
        "minutes": 27,
        "clock": {
            "limit": 60,
            "increment": 0
        },
        "rated": true,
        "fullName": "Hourly Antichess Arena",
        "nbPlayers": 0,
        "variant": {
            "key": "antichess",
            "short": "Anti",
            "name": "Antichess"
        },
        "startsAt": 1781200802500,
        "finishesAt": 1781202422500,
        "status": 10,
        "perf": {
            "key": "antichess",
            "name": "Antichess",
            "position": 9
        },
        "secondsToStart": 8173,
        "schedule": {
            "freq": "hourly",
            "speed": "bullet"
        }
    },
    {
        "id": "zwIlekkN",
        "createdBy": "lichess",
        "system": "arena",
        "minutes": 57,
        "clock": {
            "limit": 180,
            "increment": 0
        },
        "rated": true,
        "fullName": "≤1500 SuperBlitz Arena",
        "nbPlayers": 0,
        "variant": {
            "key": "standard",
            "short": "Std",
            "name": "Standard"
        },
        "startsAt": 1781200805000,
        "finishesAt": 1781204225000,
        "status": 10,
        "perf": {
            "key": "blitz",
            "name": "Blitz",
            "position": 1,
            "icon": ")"
        },
        "secondsToStart": 8176,
        "hasMaxRating": true,
        "maxRating": {
            "rating": 1500
        },
        "minRatedGames": {
            "nb": 20
        },
        "schedule": {
            "freq": "hourly",
            "speed": "superBlitz"
        }
    },
    {
        "id": "fd8uTHuZ",
        "createdBy": "lichess",
        "system": "arena",
        "minutes": 57,
        "clock": {
            "limit": 180,
            "increment": 0
        },
        "rated": true,
        "fullName": "Hourly Three-check Arena",
        "nbPlayers": 0,
        "variant": {
            "key": "threeCheck",
            "short": "3check",
            "name": "Three-check"
        },
        "startsAt": 1781200807500,
        "finishesAt": 1781204227500,
        "status": 10,
        "perf": {
            "key": "threeCheck",
            "name": "Three-Check",
            "position": 8
        },
        "secondsToStart": 8178,
        "schedule": {
            "freq": "hourly",
            "speed": "superBlitz"
        }
    },
    {
        "id": "i7kZtEDl",
        "createdBy": "lichess",
        "system": "arena",
        "minutes": 57,
        "clock": {
            "limit": 600,
            "increment": 0
        },
        "rated": true,
        "fullName": "≤2000 Rapid Arena",
        "nbPlayers": 2,
        "variant": {
            "key": "standard",
            "short": "Std",
            "name": "Standard"
        },
        "startsAt": 1781200810000,
        "finishesAt": 1781204230000,
        "status": 10,
        "perf": {
            "key": "rapid",
            "name": "Rapid",
            "position": 2,
            "icon": "#"
        },
        "secondsToStart": 8181,
        "hasMaxRating": true,
        "maxRating": {
            "rating": 2000
        },
        "minRatedGames": {
            "nb": 20
        },
        "schedule": {
            "freq": "hourly",
            "speed": "rapid"
        }
    },
    {
        "id": "pGHWDgmj",
        "createdBy": "lichess",
        "system": "arena",
        "minutes": 57,
        "clock": {
            "limit": 180,
            "increment": 2
        },
        "rated": true,
        "fullName": "Hourly King of the Hill Arena",
        "nbPlayers": 0,
        "variant": {
            "key": "kingOfTheHill",
            "short": "KotH",
            "name": "King of the Hill"
        },
        "startsAt": 1781200812500,
        "finishesAt": 1781204232500,
        "status": 10,
        "perf": {
            "key": "kingOfTheHill",
            "name": "King of the Hill",
            "position": 7
        },
        "secondsToStart": 8183,
        "schedule": {
            "freq": "hourly",
            "speed": "blitz"
        }
    },
    {
        "id": "9DdtX53r",
        "createdBy": "lichess",
        "system": "arena",
        "minutes": 27,
        "clock": {
            "limit": 30,
            "increment": 0
        },
        "rated": true,
        "fullName": "Hourly HyperBullet Arena",
        "nbPlayers": 0,
        "variant": {
            "key": "standard",
            "short": "Std",
            "name": "Standard"
        },
        "startsAt": 1781200815000,
        "finishesAt": 1781202435000,
        "status": 10,
        "perf": {
            "key": "bullet",
            "name": "Bullet",
            "position": 0,
            "icon": "T"
        },
        "secondsToStart": 8186,
        "minRatedGames": {
            "nb": 20
        },
        "schedule": {
            "freq": "hourly",
            "speed": "hyperBullet"
        }
    },
    {
        "id": "oKqcb3sE",
        "createdBy": "lichess",
        "system": "arena",
        "minutes": 27,
        "clock": {
            "limit": 60,
            "increment": 0
        },
        "rated": true,
        "fullName": "Hourly Horde Arena",
        "nbPlayers": 0,
        "variant": {
            "key": "horde",
            "short": "Horde",
            "name": "Horde"
        },
        "startsAt": 1781200817500,
        "finishesAt": 1781202437500,
        "status": 10,
        "perf": {
            "key": "horde",
            "name": "Horde",
            "position": 11
        },
        "secondsToStart": 8188,
        "schedule": {
            "freq": "hourly",
            "speed": "bullet"
        }
    },
    {
        "id": "LW9l3OTI",
        "createdBy": "lichess",
        "system": "arena",
        "minutes": 60,
        "clock": {
            "limit": 180,
            "increment": 0
        },
        "rated": true,
        "fullName": "Daily Atomic Arena",
        "nbPlayers": 0,
        "variant": {
            "key": "atomic",
            "short": "Atom",
            "name": "Atomic"
        },
        "startsAt": 1781200820000,
        "finishesAt": 1781204420000,
        "status": 10,
        "perf": {
            "key": "atomic",
            "name": "Atomic",
            "position": 10
        },
        "secondsToStart": 8191,
        "minRatedGames": {
            "nb": 15
        },
        "schedule": {
            "freq": "daily",
            "speed": "superBlitz"
        }
    },
    {
        "id": "v6hOs0Hf",
        "createdBy": "lichess",
        "system": "arena",
        "minutes": 27,
        "clock": {
            "limit": 60,
            "increment": 0
        },
        "rated": true,
        "fullName": "Hourly Bullet Arena",
        "nbPlayers": 0,
        "variant": {
            "key": "standard",
            "short": "Std",
            "name": "Standard"
        },
        "startsAt": 1781200825000,
        "finishesAt": 1781202445000,
        "status": 10,
        "perf": {
            "key": "bullet",
            "name": "Bullet",
            "position": 0,
            "icon": "T"
        },
        "secondsToStart": 8196,
        "minRatedGames": {
            "nb": 20
        },
        "schedule": {
            "freq": "hourly",
            "speed": "bullet"
        }
    },
    {
        "id": "w7IPQ6Op",
        "createdBy": "lichess",
        "system": "arena",
        "minutes": 27,
        "clock": {
            "limit": 60,
            "increment": 0
        },
        "rated": true,
        "fullName": "≤1700 Bullet Arena",
        "nbPlayers": 0,
        "variant": {
            "key": "standard",
            "short": "Std",
            "name": "Standard"
        },
        "startsAt": 1781200830000,
        "finishesAt": 1781202450000,
        "status": 10,
        "perf": {
            "key": "bullet",
            "name": "Bullet",
            "position": 0,
            "icon": "T"
        },
        "secondsToStart": 8201,
        "hasMaxRating": true,
        "maxRating": {
            "rating": 1700
        },
        "minRatedGames": {
            "nb": 20
        },
        "schedule": {
            "freq": "hourly",
            "speed": "bullet"
        }
    },
    {
        "id": "WEMExtM1",
        "createdBy": "lichess",
        "system": "arena",
        "minutes": 57,
        "clock": {
            "limit": 300,
            "increment": 0
        },
        "rated": true,
        "fullName": "≤1300 Blitz Arena",
        "nbPlayers": 0,
        "variant": {
            "key": "standard",
            "short": "Std",
            "name": "Standard"
        },
        "startsAt": 1781200835000,
        "finishesAt": 1781204255000,
        "status": 10,
        "perf": {
            "key": "blitz",
            "name": "Blitz",
            "position": 1,
            "icon": ")"
        },
        "secondsToStart": 8206,
        "hasMaxRating": true,
        "maxRating": {
            "rating": 1300
        },
        "minRatedGames": {
            "nb": 20
        },
        "schedule": {
            "freq": "hourly",
            "speed": "blitz"
        }
    },
    {
        "id": "39gGO9v7",
        "createdBy": "lichess",
        "system": "arena",
        "minutes": 90,
        "clock": {
            "limit": 180,
            "increment": 2
        },
        "rated": true,
        "fullName": "Daily Crazyhouse Arena",
        "nbPlayers": 0,
        "variant": {
            "key": "crazyhouse",
            "short": "Crazy",
            "name": "Crazyhouse"
        },
        "startsAt": 1781200840000,
        "finishesAt": 1781206240000,
        "status": 10,
        "perf": {
            "key": "crazyhouse",
            "name": "Crazyhouse",
            "position": 5
        },
        "secondsToStart": 8211,
        "minRatedGames": {
            "nb": 15
        },
        "schedule": {
            "freq": "daily",
            "speed": "blitz"
        }
    },
    {
        "id": "oP2yiqkN",
        "createdBy": "lichess",
        "system": "arena",
        "minutes": 27,
        "clock": {
            "limit": 60,
            "increment": 1
        },
        "rated": true,
        "fullName": "≤1700 Bullet Arena",
        "nbPlayers": 0,
        "variant": {
            "key": "standard",
            "short": "Std",
            "name": "Standard"
        },
        "startsAt": 1781202600000,
        "finishesAt": 1781204220000,
        "status": 10,
        "perf": {
            "key": "bullet",
            "name": "Bullet",
            "position": 0,
            "icon": "T"
        },
        "secondsToStart": 9971,
        "hasMaxRating": true,
        "maxRating": {
            "rating": 1700
        },
        "minRatedGames": {
            "nb": 20
        },
        "schedule": {
            "freq": "hourly",
            "speed": "bullet"
        }
    },
    {
        "id": "32VokgtQ",
        "createdBy": "lichess",
        "system": "arena",
        "minutes": 27,
        "clock": {
            "limit": 30,
            "increment": 0
        },
        "rated": true,
        "fullName": "Hourly Antichess Arena",
        "nbPlayers": 0,
        "variant": {
            "key": "antichess",
            "short": "Anti",
            "name": "Antichess"
        },
        "startsAt": 1781202610000,
        "finishesAt": 1781204230000,
        "status": 10,
        "perf": {
            "key": "antichess",
            "name": "Antichess",
            "position": 9
        },
        "secondsToStart": 9981,
        "schedule": {
            "freq": "hourly",
            "speed": "hyperBullet"
        }
    },
    {
        "id": "X0UUUX4m",
        "createdBy": "lichess",
        "system": "arena",
        "minutes": 27,
        "clock": {
            "limit": 60,
            "increment": 0
        },
        "rated": true,
        "fullName": "Hourly Bullet Arena",
        "nbPlayers": 0,
        "variant": {
            "key": "standard",
            "short": "Std",
            "name": "Standard"
        },
        "startsAt": 1781202620000,
        "finishesAt": 1781204240000,
        "status": 10,
        "perf": {
            "key": "bullet",
            "name": "Bullet",
            "position": 0,
            "icon": "T"
        },
        "secondsToStart": 9991,
        "minRatedGames": {
            "nb": 20
        },
        "schedule": {
            "freq": "hourly",
            "speed": "bullet"
        }
    },
    {
        "id": "F96tM1SS",
        "createdBy": "lichess",
        "system": "arena",
        "minutes": 27,
        "clock": {
            "limit": 60,
            "increment": 0
        },
        "rated": true,
        "fullName": "Hourly Horde Arena",
        "nbPlayers": 0,
        "variant": {
            "key": "horde",
            "short": "Horde",
            "name": "Horde"
        },
        "startsAt": 1781202630000,
        "finishesAt": 1781204250000,
        "status": 10,
        "perf": {
            "key": "horde",
            "name": "Horde",
            "position": 11
        },
        "secondsToStart": 10001,
        "schedule": {
            "freq": "hourly",
            "speed": "bullet"
        }
    },
    {
        "id": "FKBfGD34",
        "createdBy": "lichess",
        "system": "arena",
        "minutes": 27,
        "clock": {
            "limit": 15,
            "increment": 0
        },
        "rated": true,
        "fullName": "Hourly UltraBullet Arena",
        "nbPlayers": 1,
        "variant": {
            "key": "standard",
            "short": "Std",
            "name": "Standard"
        },
        "startsAt": 1781202640000,
        "finishesAt": 1781204260000,
        "status": 10,
        "perf": {
            "key": "ultraBullet",
            "name": "UltraBullet",
            "position": 4,
            "icon": "{"
        },
        "secondsToStart": 10011,
        "schedule": {
            "freq": "hourly",
            "speed": "ultraBullet"
        }
    },
    {
        "id": "pf10GYGi",
        "createdBy": "lichess",
        "system": "arena",
        "minutes": 180,
        "clock": {
            "limit": 180,
            "increment": 0
        },
        "rated": true,
        "fullName": "Weekly Racing Kings Arena",
        "nbPlayers": 2,
        "variant": {
            "key": "racingKings",
            "short": "Racing",
            "name": "Racing Kings"
        },
        "startsAt": 1781204400000,
        "finishesAt": 1781215200000,
        "status": 10,
        "perf": {
            "key": "racingKings",
            "name": "Racing Kings",
            "position": 12
        },
        "secondsToStart": 11771,
        "minRatedGames": {
            "nb": 20
        },
        "schedule": {
            "freq": "weekly",
            "speed": "superBlitz"
        }
    },
    {
        "id": "XXzhA7Ni",
        "createdBy": "lichess",
        "system": "arena",
        "minutes": 57,
        "clock": {
            "limit": 600,
            "increment": 0
        },
        "rated": true,
        "fullName": "≤1300 Rapid Arena",
        "nbPlayers": 3,
        "variant": {
            "key": "standard",
            "short": "Std",
            "name": "Standard"
        },
        "startsAt": 1781204402500,
        "finishesAt": 1781207822500,
        "status": 10,
        "perf": {
            "key": "rapid",
            "name": "Rapid",
            "position": 2,
            "icon": "#"
        },
        "secondsToStart": 11773,
        "hasMaxRating": true,
        "maxRating": {
            "rating": 1300
        },
        "minRatedGames": {
            "nb": 20
        },
        "schedule": {
            "freq": "hourly",
            "speed": "rapid"
        }
    },
    {
        "id": "5yuNOzWS",
        "createdBy": "lichess",
        "system": "arena",
        "minutes": 57,
        "clock": {
            "limit": 180,
            "increment": 0
        },
        "rated": true,
        "fullName": "≤1700 SuperBlitz Arena",
        "nbPlayers": 0,
        "variant": {
            "key": "standard",
            "short": "Std",
            "name": "Standard"
        },
        "startsAt": 1781204405000,
        "finishesAt": 1781207825000,
        "status": 10,
        "perf": {
            "key": "blitz",
            "name": "Blitz",
            "position": 1,
            "icon": ")"
        },
        "secondsToStart": 11776,
        "hasMaxRating": true,
        "maxRating": {
            "rating": 1700
        },
        "minRatedGames": {
            "nb": 20
        },
        "schedule": {
            "freq": "hourly",
            "speed": "superBlitz"
        }
    },
    {
        "id": "I7FBQzx4",
        "createdBy": "lichess",
        "system": "arena",
        "minutes": 27,
        "clock": {
            "limit": 60,
            "increment": 0
        },
        "rated": true,
        "fullName": "Hourly Atomic Arena",
        "nbPlayers": 0,
        "variant": {
            "key": "atomic",
            "short": "Atom",
            "name": "Atomic"
        },
        "startsAt": 1781204407500,
        "finishesAt": 1781206027500,
        "status": 10,
        "perf": {
            "key": "atomic",
            "name": "Atomic",
            "position": 10
        },
        "secondsToStart": 11778,
        "schedule": {
            "freq": "hourly",
            "speed": "bullet"
        }
    },
    {
        "id": "hRFUfuaL",
        "createdBy": "lichess",
        "system": "arena",
        "minutes": 27,
        "clock": {
            "limit": 60,
            "increment": 0
        },
        "rated": true,
        "fullName": "Queen's Gambit Declined Bullet Arena",
        "nbPlayers": 0,
        "variant": {
            "key": "standard",
            "short": "Std",
            "name": "Standard"
        },
        "startsAt": 1781204410000,
        "finishesAt": 1781206030000,
        "status": 10,
        "perf": {
            "key": "bullet",
            "name": "Bullet",
            "position": 0,
            "icon": "T"
        },
        "secondsToStart": 11781,
        "minRatedGames": {
            "nb": 20
        },
        "position": {
            "eco": "D07",
            "name": "Queen's Gambit Declined: Chigorin Defense",
            "fen": "r1bqkbnr/ppp1pppp/2n5/3p4/2PP4/8/PP2PPPP/RNBQKBNR w KQkq -",
            "url": "https://lichess.org/opening/Queens_Gambit_Declined_Chigorin_Defense"
        },
        "schedule": {
            "freq": "hourly",
            "speed": "bullet"
        }
    },
    {
        "id": "s5dceYKl",
        "createdBy": "lichess",
        "system": "arena",
        "minutes": 27,
        "clock": {
            "limit": 60,
            "increment": 0
        },
        "rated": true,
        "fullName": "Hourly King of the Hill Arena",
        "nbPlayers": 0,
        "variant": {
            "key": "kingOfTheHill",
            "short": "KotH",
            "name": "King of the Hill"
        },
        "startsAt": 1781204412500,
        "finishesAt": 1781206032500,
        "status": 10,
        "perf": {
            "key": "kingOfTheHill",
            "name": "King of the Hill",
            "position": 7
        },
        "secondsToStart": 11783,
        "schedule": {
            "freq": "hourly",
            "speed": "bullet"
        }
    },
    {
        "id": "lx4duDLu",
        "createdBy": "lichess",
        "system": "arena",
        "minutes": 57,
        "clock": {
            "limit": 180,
            "increment": 2
        },
        "rated": true,
        "fullName": "≤1500 Blitz Arena",
        "nbPlayers": 0,
        "variant": {
            "key": "standard",
            "short": "Std",
            "name": "Standard"
        },
        "startsAt": 1781204415000,
        "finishesAt": 1781207835000,
        "status": 10,
        "perf": {
            "key": "blitz",
            "name": "Blitz",
            "position": 1,
            "icon": ")"
        },
        "secondsToStart": 11786,
        "hasMaxRating": true,
        "maxRating": {
            "rating": 1500
        },
        "minRatedGames": {
            "nb": 20
        },
        "schedule": {
            "freq": "hourly",
            "speed": "blitz"
        }
    },
    {
        "id": "ljFNczl3",
        "createdBy": "lichess",
        "system": "arena",
        "minutes": 60,
        "clock": {
            "limit": 180,
            "increment": 0
        },
        "rated": true,
        "fullName": "Daily Antichess Arena",
        "nbPlayers": 0,
        "variant": {
            "key": "antichess",
            "short": "Anti",
            "name": "Antichess"
        },
        "startsAt": 1781204420000,
        "finishesAt": 1781208020000,
        "status": 10,
        "perf": {
            "key": "antichess",
            "name": "Antichess",
            "position": 9
        },
        "secondsToStart": 11791,
        "minRatedGames": {
            "nb": 15
        },
        "schedule": {
            "freq": "daily",
            "speed": "superBlitz"
        }
    },
    {
        "id": "LicvAMbl",
        "createdBy": "lichess",
        "system": "arena",
        "minutes": 27,
        "clock": {
            "limit": 30,
            "increment": 0
        },
        "rated": true,
        "fullName": "Hourly HyperBullet Arena",
        "nbPlayers": 0,
        "variant": {
            "key": "standard",
            "short": "Std",
            "name": "Standard"
        },
        "startsAt": 1781204425000,
        "finishesAt": 1781206045000,
        "status": 10,
        "perf": {
            "key": "bullet",
            "name": "Bullet",
            "position": 0,
            "icon": "T"
        },
        "secondsToStart": 11796,
        "minRatedGames": {
            "nb": 20
        },
        "schedule": {
            "freq": "hourly",
            "speed": "hyperBullet"
        }
    },
    {
        "id": "DAMBwXnH",
        "createdBy": "lichess",
        "system": "arena",
        "minutes": 27,
        "clock": {
            "limit": 60,
            "increment": 0
        },
        "rated": true,
        "fullName": "≤2000 Bullet Arena",
        "nbPlayers": 0,
        "variant": {
            "key": "standard",
            "short": "Std",
            "name": "Standard"
        },
        "startsAt": 1781204430000,
        "finishesAt": 1781206050000,
        "status": 10,
        "perf": {
            "key": "bullet",
            "name": "Bullet",
            "position": 0,
            "icon": "T"
        },
        "secondsToStart": 11801,
        "hasMaxRating": true,
        "maxRating": {
            "rating": 2000
        },
        "minRatedGames": {
            "nb": 20
        },
        "schedule": {
            "freq": "hourly",
            "speed": "bullet"
        }
    },
    {
        "id": "VbDAnduJ",
        "createdBy": "lichess",
        "system": "arena",
        "minutes": 57,
        "clock": {
            "limit": 180,
            "increment": 0
        },
        "rated": true,
        "fullName": "Hourly SuperBlitz Arena",
        "nbPlayers": 0,
        "variant": {
            "key": "standard",
            "short": "Std",
            "name": "Standard"
        },
        "startsAt": 1781204435000,
        "finishesAt": 1781207855000,
        "status": 10,
        "perf": {
            "key": "blitz",
            "name": "Blitz",
            "position": 1,
            "icon": ")"
        },
        "secondsToStart": 11806,
        "minRatedGames": {
            "nb": 15
        },
        "schedule": {
            "freq": "hourly",
            "speed": "superBlitz"
        }
    },
    {
        "id": "5TJCNluL",
        "createdBy": "lichess",
        "system": "arena",
        "minutes": 90,
        "clock": {
            "limit": 180,
            "increment": 2
        },
        "rated": true,
        "fullName": "Daily Chess960 Arena",
        "nbPlayers": 0,
        "variant": {
            "key": "chess960",
            "short": "960",
            "name": "Chess960"
        },
        "startsAt": 1781204440000,
        "finishesAt": 1781209840000,
        "status": 10,
        "perf": {
            "key": "chess960",
            "name": "Chess960",
            "position": 6
        },
        "secondsToStart": 11811,
        "minRatedGames": {
            "nb": 15
        },
        "schedule": {
            "freq": "daily",
            "speed": "blitz"
        }
    },
    {
        "id": "T1kbUork",
        "createdBy": "lichess",
        "system": "arena",
        "minutes": 27,
        "clock": {
            "limit": 60,
            "increment": 1
        },
        "rated": true,
        "fullName": "≤2000 Bullet Arena",
        "nbPlayers": 0,
        "variant": {
            "key": "standard",
            "short": "Std",
            "name": "Standard"
        },
        "startsAt": 1781206200000,
        "finishesAt": 1781207820000,
        "status": 10,
        "perf": {
            "key": "bullet",
            "name": "Bullet",
            "position": 0,
            "icon": "T"
        },
        "secondsToStart": 13571,
        "hasMaxRating": true,
        "maxRating": {
            "rating": 2000
        },
        "minRatedGames": {
            "nb": 20
        },
        "schedule": {
            "freq": "hourly",
            "speed": "bullet"
        }
    },
    {
        "id": "6wIR1MVB",
        "createdBy": "lichess",
        "system": "arena",
        "minutes": 27,
        "clock": {
            "limit": 30,
            "increment": 0
        },
        "rated": true,
        "fullName": "Hourly King of the Hill Arena",
        "nbPlayers": 0,
        "variant": {
            "key": "kingOfTheHill",
            "short": "KotH",
            "name": "King of the Hill"
        },
        "startsAt": 1781206205000,
        "finishesAt": 1781207825000,
        "status": 10,
        "perf": {
            "key": "kingOfTheHill",
            "name": "King of the Hill",
            "position": 7
        },
        "secondsToStart": 13576,
        "schedule": {
            "freq": "hourly",
            "speed": "hyperBullet"
        }
    },
    {
        "id": "iQAGNEcX",
        "createdBy": "lichess",
        "system": "arena",
        "minutes": 27,
        "clock": {
            "limit": 30,
            "increment": 0
        },
        "rated": true,
        "fullName": "Hourly Atomic Arena",
        "nbPlayers": 1,
        "variant": {
            "key": "atomic",
            "short": "Atom",
            "name": "Atomic"
        },
        "startsAt": 1781206210000,
        "finishesAt": 1781207830000,
        "status": 10,
        "perf": {
            "key": "atomic",
            "name": "Atomic",
            "position": 10
        },
        "secondsToStart": 13581,
        "schedule": {
            "freq": "hourly",
            "speed": "hyperBullet"
        }
    },
    {
        "id": "iA7bvfol",
        "createdBy": "lichess",
        "system": "arena",
        "minutes": 27,
        "clock": {
            "limit": 60,
            "increment": 0
        },
        "rated": true,
        "fullName": "Hourly Bullet Arena",
        "nbPlayers": 0,
        "variant": {
            "key": "standard",
            "short": "Std",
            "name": "Standard"
        },
        "startsAt": 1781206220000,
        "finishesAt": 1781207840000,
        "status": 10,
        "perf": {
            "key": "bullet",
            "name": "Bullet",
            "position": 0,
            "icon": "T"
        },
        "secondsToStart": 13591,
        "minRatedGames": {
            "nb": 20
        },
        "schedule": {
            "freq": "hourly",
            "speed": "bullet"
        }
    },
    {
        "id": "WR07y2vm",
        "createdBy": "lichess",
        "system": "arena",
        "minutes": 27,
        "clock": {
            "limit": 30,
            "increment": 0
        },
        "rated": true,
        "fullName": "Hourly Crazyhouse Arena",
        "nbPlayers": 0,
        "variant": {
            "key": "crazyhouse",
            "short": "Crazy",
            "name": "Crazyhouse"
        },
        "startsAt": 1781206230000,
        "finishesAt": 1781207850000,
        "status": 10,
        "perf": {
            "key": "crazyhouse",
            "name": "Crazyhouse",
            "position": 5
        },
        "secondsToStart": 13601,
        "schedule": {
            "freq": "hourly",
            "speed": "hyperBullet"
        }
    },
    {
        "id": "vED6rAUa",
        "createdBy": "lichess",
        "system": "arena",
        "minutes": 27,
        "clock": {
            "limit": 15,
            "increment": 0
        },
        "rated": true,
        "fullName": "Hourly UltraBullet Arena",
        "nbPlayers": 1,
        "variant": {
            "key": "standard",
            "short": "Std",
            "name": "Standard"
        },
        "startsAt": 1781206240000,
        "finishesAt": 1781207860000,
        "status": 10,
        "perf": {
            "key": "ultraBullet",
            "name": "UltraBullet",
            "position": 4,
            "icon": "{"
        },
        "secondsToStart": 13611,
        "schedule": {
            "freq": "hourly",
            "speed": "ultraBullet"
        }
    },
    {
        "id": "92HR7e5d",
        "createdBy": "lichess",
        "system": "arena",
        "minutes": 60,
        "clock": {
            "limit": 180,
            "increment": 0
        },
        "rated": true,
        "fullName": "Daily Three-check Arena",
        "nbPlayers": 0,
        "variant": {
            "key": "threeCheck",
            "short": "3check",
            "name": "Three-check"
        },
        "startsAt": 1781208000000,
        "finishesAt": 1781211600000,
        "status": 10,
        "perf": {
            "key": "threeCheck",
            "name": "Three-Check",
            "position": 8
        },
        "secondsToStart": 15371,
        "minRatedGames": {
            "nb": 15
        },
        "schedule": {
            "freq": "daily",
            "speed": "superBlitz"
        }
    },
    {
        "id": "7xg3B4YD",
        "createdBy": "lichess",
        "system": "arena",
        "minutes": 27,
        "clock": {
            "limit": 60,
            "increment": 0
        },
        "rated": true,
        "fullName": "≤1300 Bullet Arena",
        "nbPlayers": 0,
        "variant": {
            "key": "standard",
            "short": "Std",
            "name": "Standard"
        },
        "startsAt": 1781208002500,
        "finishesAt": 1781209622500,
        "status": 10,
        "perf": {
            "key": "bullet",
            "name": "Bullet",
            "position": 0,
            "icon": "T"
        },
        "secondsToStart": 15373,
        "hasMaxRating": true,
        "maxRating": {
            "rating": 1300
        },
        "minRatedGames": {
            "nb": 20
        },
        "schedule": {
            "freq": "hourly",
            "speed": "bullet"
        }
    },
    {
        "id": "re9HMchv",
        "createdBy": "lichess",
        "system": "arena",
        "minutes": 57,
        "clock": {
            "limit": 300,
            "increment": 0
        },
        "rated": true,
        "fullName": "≤1700 Blitz Arena",
        "nbPlayers": 0,
        "variant": {
            "key": "standard",
            "short": "Std",
            "name": "Standard"
        },
        "startsAt": 1781208005000,
        "finishesAt": 1781211425000,
        "status": 10,
        "perf": {
            "key": "blitz",
            "name": "Blitz",
            "position": 1,
            "icon": ")"
        },
        "secondsToStart": 15376,
        "hasMaxRating": true,
        "maxRating": {
            "rating": 1700
        },
        "minRatedGames": {
            "nb": 20
        },
        "schedule": {
            "freq": "hourly",
            "speed": "blitz"
        }
    },
    {
        "id": "IMsNh6IF",
        "createdBy": "lichess",
        "system": "arena",
        "minutes": 57,
        "clock": {
            "limit": 180,
            "increment": 0
        },
        "rated": true,
        "fullName": "Hourly Antichess Arena",
        "nbPlayers": 0,
        "variant": {
            "key": "antichess",
            "short": "Anti",
            "name": "Antichess"
        },
        "startsAt": 1781208007500,
        "finishesAt": 1781211427500,
        "status": 10,
        "perf": {
            "key": "antichess",
            "name": "Antichess",
            "position": 9
        },
        "secondsToStart": 15378,
        "schedule": {
            "freq": "hourly",
            "speed": "superBlitz"
        }
    },
    {
        "id": "hHD7Ume7",
        "createdBy": "lichess",
        "system": "arena",
        "minutes": 57,
        "clock": {
            "limit": 180,
            "increment": 0
        },
        "rated": true,
        "fullName": "Queen's Gambit Declined SuperBlitz Arena",
        "nbPlayers": 0,
        "variant": {
            "key": "standard",
            "short": "Std",
            "name": "Standard"
        },
        "startsAt": 1781208010000,
        "finishesAt": 1781211430000,
        "status": 10,
        "perf": {
            "key": "blitz",
            "name": "Blitz",
            "position": 1,
            "icon": ")"
        },
        "secondsToStart": 15381,
        "minRatedGames": {
            "nb": 15
        },
        "position": {
            "eco": "D07",
            "name": "Queen's Gambit Declined: Chigorin Defense",
            "fen": "r1bqkbnr/ppp1pppp/2n5/3p4/2PP4/8/PP2PPPP/RNBQKBNR w KQkq -",
            "url": "https://lichess.org/opening/Queens_Gambit_Declined_Chigorin_Defense"
        },
        "schedule": {
            "freq": "hourly",
            "speed": "superBlitz"
        }
    },
    {
        "id": "0Cst0KsV",
        "createdBy": "lichess",
        "system": "arena",
        "minutes": 57,
        "clock": {
            "limit": 180,
            "increment": 0
        },
        "rated": true,
        "fullName": "Hourly Atomic Arena",
        "nbPlayers": 0,
        "variant": {
            "key": "atomic",
            "short": "Atom",
            "name": "Atomic"
        },
        "startsAt": 1781208012500,
        "finishesAt": 1781211432500,
        "status": 10,
        "perf": {
            "key": "atomic",
            "name": "Atomic",
            "position": 10
        },
        "secondsToStart": 15383,
        "schedule": {
            "freq": "hourly",
            "speed": "superBlitz"
        }
    },
    {
        "id": "YEaoa41X",
        "createdBy": "lichess",
        "system": "arena",
        "minutes": 57,
        "clock": {
            "limit": 600,
            "increment": 0
        },
        "rated": true,
        "fullName": "≤1500 Rapid Arena",
        "nbPlayers": 0,
        "variant": {
            "key": "standard",
            "short": "Std",
            "name": "Standard"
        },
        "startsAt": 1781208015000,
        "finishesAt": 1781211435000,
        "status": 10,
        "perf": {
            "key": "rapid",
            "name": "Rapid",
            "position": 2,
            "icon": "#"
        },
        "secondsToStart": 15386,
        "hasMaxRating": true,
        "maxRating": {
            "rating": 1500
        },
        "minRatedGames": {
            "nb": 20
        },
        "schedule": {
            "freq": "hourly",
            "speed": "rapid"
        }
    },
    {
        "id": "u0pr4YFk",
        "createdBy": "lichess",
        "system": "arena",
        "minutes": 60,
        "clock": {
            "limit": 30,
            "increment": 0
        },
        "rated": true,
        "fullName": "Daily HyperBullet Arena",
        "nbPlayers": 2,
        "variant": {
            "key": "standard",
            "short": "Std",
            "name": "Standard"
        },
        "startsAt": 1781208020000,
        "finishesAt": 1781211620000,
        "status": 10,
        "perf": {
            "key": "bullet",
            "name": "Bullet",
            "position": 0,
            "icon": "T"
        },
        "secondsToStart": 15391,
        "minRatedGames": {
            "nb": 20
        },
        "schedule": {
            "freq": "daily",
            "speed": "hyperBullet"
        }
    },
    {
        "id": "inx0h3BO",
        "createdBy": "lichess",
        "system": "arena",
        "minutes": 27,
        "clock": {
            "limit": 60,
            "increment": 0
        },
        "rated": true,
        "fullName": "Hourly Bullet Arena",
        "nbPlayers": 0,
        "variant": {
            "key": "standard",
            "short": "Std",
            "name": "Standard"
        },
        "startsAt": 1781208025000,
        "finishesAt": 1781209645000,
        "status": 10,
        "perf": {
            "key": "bullet",
            "name": "Bullet",
            "position": 0,
            "icon": "T"
        },
        "secondsToStart": 15396,
        "minRatedGames": {
            "nb": 20
        },
        "schedule": {
            "freq": "hourly",
            "speed": "bullet"
        }
    },
    {
        "id": "G4Q8XEyZ",
        "createdBy": "lichess",
        "system": "arena",
        "minutes": 57,
        "clock": {
            "limit": 180,
            "increment": 0
        },
        "rated": true,
        "fullName": "≤2000 SuperBlitz Arena",
        "nbPlayers": 0,
        "variant": {
            "key": "standard",
            "short": "Std",
            "name": "Standard"
        },
        "startsAt": 1781208030000,
        "finishesAt": 1781211450000,
        "status": 10,
        "perf": {
            "key": "blitz",
            "name": "Blitz",
            "position": 1,
            "icon": ")"
        },
        "secondsToStart": 15401,
        "hasMaxRating": true,
        "maxRating": {
            "rating": 2000
        },
        "minRatedGames": {
            "nb": 20
        },
        "schedule": {
            "freq": "hourly",
            "speed": "superBlitz"
        }
    },
    {
        "id": "0p48bwAN",
        "createdBy": "lichess",
        "system": "arena",
        "minutes": 57,
        "clock": {
            "limit": 300,
            "increment": 0
        },
        "rated": true,
        "fullName": "Hourly Blitz Arena",
        "nbPlayers": 0,
        "variant": {
            "key": "standard",
            "short": "Std",
            "name": "Standard"
        },
        "startsAt": 1781208035000,
        "finishesAt": 1781211455000,
        "status": 10,
        "perf": {
            "key": "blitz",
            "name": "Blitz",
            "position": 1,
            "icon": ")"
        },
        "secondsToStart": 15406,
        "minRatedGames": {
            "nb": 15
        },
        "schedule": {
            "freq": "hourly",
            "speed": "blitz"
        }
    },
    {
        "id": "AAckl33v",
        "createdBy": "lichess",
        "system": "arena",
        "minutes": 60,
        "clock": {
            "limit": 180,
            "increment": 0
        },
        "rated": true,
        "fullName": "Daily Horde Arena",
        "nbPlayers": 0,
        "variant": {
            "key": "horde",
            "short": "Horde",
            "name": "Horde"
        },
        "startsAt": 1781208040000,
        "finishesAt": 1781211640000,
        "status": 10,
        "perf": {
            "key": "horde",
            "name": "Horde",
            "position": 11
        },
        "secondsToStart": 15411,
        "minRatedGames": {
            "nb": 15
        },
        "schedule": {
            "freq": "daily",
            "speed": "superBlitz"
        }
    },
    {
        "id": "7av1athA",
        "createdBy": "lichess",
        "system": "arena",
        "minutes": 27,
        "clock": {
            "limit": 60,
            "increment": 0
        },
        "rated": true,
        "fullName": "Hourly Bullet Arena",
        "nbPlayers": 0,
        "variant": {
            "key": "standard",
            "short": "Std",
            "name": "Standard"
        },
        "startsAt": 1781209800000,
        "finishesAt": 1781211420000,
        "status": 10,
        "perf": {
            "key": "bullet",
            "name": "Bullet",
            "position": 0,
            "icon": "T"
        },
        "secondsToStart": 17171,
        "minRatedGames": {
            "nb": 20
        },
        "schedule": {
            "freq": "hourly",
            "speed": "bullet"
        }
    },
    {
        "id": "HN3vDuTx",
        "createdBy": "lichess",
        "system": "arena",
        "minutes": 27,
        "clock": {
            "limit": 60,
            "increment": 0
        },
        "rated": true,
        "fullName": "Hourly Chess960 Arena",
        "nbPlayers": 1,
        "variant": {
            "key": "chess960",
            "short": "960",
            "name": "Chess960"
        },
        "startsAt": 1781209820000,
        "finishesAt": 1781211440000,
        "status": 10,
        "perf": {
            "key": "chess960",
            "name": "Chess960",
            "position": 6
        },
        "secondsToStart": 17191,
        "schedule": {
            "freq": "hourly",
            "speed": "bullet"
        }
    },
    {
        "id": "8V2V2BuF",
        "createdBy": "lichess",
        "system": "arena",
        "minutes": 27,
        "clock": {
            "limit": 60,
            "increment": 1
        },
        "rated": true,
        "fullName": "≤1300 Bullet Arena",
        "nbPlayers": 0,
        "variant": {
            "key": "standard",
            "short": "Std",
            "name": "Standard"
        },
        "startsAt": 1781209840000,
        "finishesAt": 1781211460000,
        "status": 10,
        "perf": {
            "key": "bullet",
            "name": "Bullet",
            "position": 0,
            "icon": "T"
        },
        "secondsToStart": 17211,
        "hasMaxRating": true,
        "maxRating": {
            "rating": 1300
        },
        "minRatedGames": {
            "nb": 20
        },
        "schedule": {
            "freq": "hourly",
            "speed": "bullet"
        }
    },
    {
        "id": "jQVi39lp",
        "createdBy": "lichess",
        "system": "arena",
        "minutes": 60,
        "clock": {
            "limit": 15,
            "increment": 0
        },
        "rated": true,
        "fullName": "Daily UltraBullet Arena",
        "nbPlayers": 2,
        "variant": {
            "key": "standard",
            "short": "Std",
            "name": "Standard"
        },
        "startsAt": 1781211600000,
        "finishesAt": 1781215200000,
        "status": 10,
        "perf": {
            "key": "ultraBullet",
            "name": "UltraBullet",
            "position": 4,
            "icon": "{"
        },
        "secondsToStart": 18971,
        "schedule": {
            "freq": "daily",
            "speed": "ultraBullet"
        }
    },
    {
        "id": "CBtbquyX",
        "createdBy": "lichess",
        "system": "arena",
        "minutes": 27,
        "clock": {
            "limit": 60,
            "increment": 0
        },
        "rated": true,
        "fullName": "Hourly Antichess Arena",
        "nbPlayers": 0,
        "variant": {
            "key": "antichess",
            "short": "Anti",
            "name": "Antichess"
        },
        "startsAt": 1781211602500,
        "finishesAt": 1781213222500,
        "status": 10,
        "perf": {
            "key": "antichess",
            "name": "Antichess",
            "position": 9
        },
        "secondsToStart": 18973,
        "schedule": {
            "freq": "hourly",
            "speed": "bullet"
        }
    },
    {
        "id": "vEhyNfY0",
        "createdBy": "lichess",
        "system": "arena",
        "minutes": 27,
        "clock": {
            "limit": 60,
            "increment": 0
        },
        "rated": true,
        "fullName": "≤1500 Bullet Arena",
        "nbPlayers": 0,
        "variant": {
            "key": "standard",
            "short": "Std",
            "name": "Standard"
        },
        "startsAt": 1781211605000,
        "finishesAt": 1781213225000,
        "status": 10,
        "perf": {
            "key": "bullet",
            "name": "Bullet",
            "position": 0,
            "icon": "T"
        },
        "secondsToStart": 18976,
        "hasMaxRating": true,
        "maxRating": {
            "rating": 1500
        },
        "minRatedGames": {
            "nb": 20
        },
        "schedule": {
            "freq": "hourly",
            "speed": "bullet"
        }
    },
    {
        "id": "ekubIlj4",
        "createdBy": "lichess",
        "system": "arena",
        "minutes": 27,
        "clock": {
            "limit": 60,
            "increment": 0
        },
        "rated": true,
        "fullName": "Hourly Three-check Arena",
        "nbPlayers": 0,
        "variant": {
            "key": "threeCheck",
            "short": "3check",
            "name": "Three-check"
        },
        "startsAt": 1781211607500,
        "finishesAt": 1781213227500,
        "status": 10,
        "perf": {
            "key": "threeCheck",
            "name": "Three-Check",
            "position": 8
        },
        "secondsToStart": 18978,
        "schedule": {
            "freq": "hourly",
            "speed": "bullet"
        }
    },
    {
        "id": "RTOx4OCZ",
        "createdBy": "lichess",
        "system": "arena",
        "minutes": 57,
        "clock": {
            "limit": 300,
            "increment": 0
        },
        "rated": true,
        "fullName": "≤2000 Blitz Arena",
        "nbPlayers": 0,
        "variant": {
            "key": "standard",
            "short": "Std",
            "name": "Standard"
        },
        "startsAt": 1781211610000,
        "finishesAt": 1781215030000,
        "status": 10,
        "perf": {
            "key": "blitz",
            "name": "Blitz",
            "position": 1,
            "icon": ")"
        },
        "secondsToStart": 18981,
        "hasMaxRating": true,
        "maxRating": {
            "rating": 2000
        },
        "minRatedGames": {
            "nb": 20
        },
        "schedule": {
            "freq": "hourly",
            "speed": "blitz"
        }
    },
    {
        "id": "wMazgYhO",
        "createdBy": "lichess",
        "system": "arena",
        "minutes": 57,
        "clock": {
            "limit": 180,
            "increment": 2
        },
        "rated": true,
        "fullName": "Hourly Crazyhouse Arena",
        "nbPlayers": 0,
        "variant": {
            "key": "crazyhouse",
            "short": "Crazy",
            "name": "Crazyhouse"
        },
        "startsAt": 1781211612500,
        "finishesAt": 1781215032500,
        "status": 10,
        "perf": {
            "key": "crazyhouse",
            "name": "Crazyhouse",
            "position": 5
        },
        "secondsToStart": 18983,
        "schedule": {
            "freq": "hourly",
            "speed": "blitz"
        }
    },
    {
        "id": "u1AcDYlm",
        "createdBy": "lichess",
        "system": "arena",
        "minutes": 27,
        "clock": {
            "limit": 60,
            "increment": 0
        },
        "rated": true,
        "fullName": "Hourly Bullet Arena",
        "nbPlayers": 0,
        "variant": {
            "key": "standard",
            "short": "Std",
            "name": "Standard"
        },
        "startsAt": 1781211615000,
        "finishesAt": 1781213235000,
        "status": 10,
        "perf": {
            "key": "bullet",
            "name": "Bullet",
            "position": 0,
            "icon": "T"
        },
        "secondsToStart": 18986,
        "minRatedGames": {
            "nb": 20
        },
        "schedule": {
            "freq": "hourly",
            "speed": "bullet"
        }
    },
    {
        "id": "dwsjfr32",
        "createdBy": "lichess",
        "system": "arena",
        "minutes": 57,
        "clock": {
            "limit": 300,
            "increment": 0
        },
        "rated": true,
        "fullName": "Queen's Gambit Declined Blitz Arena",
        "nbPlayers": 0,
        "variant": {
            "key": "standard",
            "short": "Std",
            "name": "Standard"
        },
        "startsAt": 1781211620000,
        "finishesAt": 1781215040000,
        "status": 10,
        "perf": {
            "key": "blitz",
            "name": "Blitz",
            "position": 1,
            "icon": ")"
        },
        "secondsToStart": 18991,
        "minRatedGames": {
            "nb": 15
        },
        "position": {
            "eco": "D07",
            "name": "Queen's Gambit Declined: Chigorin Defense",
            "fen": "r1bqkbnr/ppp1pppp/2n5/3p4/2PP4/8/PP2PPPP/RNBQKBNR w KQkq -",
            "url": "https://lichess.org/opening/Queens_Gambit_Declined_Chigorin_Defense"
        },
        "schedule": {
            "freq": "hourly",
            "speed": "blitz"
        }
    },
    {
        "id": "Po1JOZwd",
        "createdBy": "lichess",
        "system": "arena",
        "minutes": 57,
        "clock": {
            "limit": 180,
            "increment": 0
        },
        "rated": true,
        "fullName": "Hourly SuperBlitz Arena",
        "nbPlayers": 0,
        "variant": {
            "key": "standard",
            "short": "Std",
            "name": "Standard"
        },
        "startsAt": 1781211625000,
        "finishesAt": 1781215045000,
        "status": 10,
        "perf": {
            "key": "blitz",
            "name": "Blitz",
            "position": 1,
            "icon": ")"
        },
        "secondsToStart": 18996,
        "minRatedGames": {
            "nb": 15
        },
        "schedule": {
            "freq": "hourly",
            "speed": "superBlitz"
        }
    },
    {
        "id": "o6mf1oN9",
        "createdBy": "lichess",
        "system": "arena",
        "minutes": 57,
        "clock": {
            "limit": 600,
            "increment": 0
        },
        "rated": true,
        "fullName": "≤1700 Rapid Arena",
        "nbPlayers": 0,
        "variant": {
            "key": "standard",
            "short": "Std",
            "name": "Standard"
        },
        "startsAt": 1781211630000,
        "finishesAt": 1781215050000,
        "status": 10,
        "perf": {
            "key": "rapid",
            "name": "Rapid",
            "position": 2,
            "icon": "#"
        },
        "secondsToStart": 19001,
        "hasMaxRating": true,
        "maxRating": {
            "rating": 1700
        },
        "minRatedGames": {
            "nb": 20
        },
        "schedule": {
            "freq": "hourly",
            "speed": "rapid"
        }
    },
    {
        "id": "VIqeBLRA",
        "createdBy": "lichess",
        "system": "arena",
        "minutes": 57,
        "clock": {
            "limit": 180,
            "increment": 0
        },
        "rated": true,
        "fullName": "≤1300 SuperBlitz Arena",
        "nbPlayers": 0,
        "variant": {
            "key": "standard",
            "short": "Std",
            "name": "Standard"
        },
        "startsAt": 1781211635000,
        "finishesAt": 1781215055000,
        "status": 10,
        "perf": {
            "key": "blitz",
            "name": "Blitz",
            "position": 1,
            "icon": ")"
        },
        "secondsToStart": 19006,
        "hasMaxRating": true,
        "maxRating": {
            "rating": 1300
        },
        "minRatedGames": {
            "nb": 20
        },
        "schedule": {
            "freq": "hourly",
            "speed": "superBlitz"
        }
    },
    {
        "id": "TUYmqaZB",
        "createdBy": "lichess",
        "system": "arena",
        "minutes": 60,
        "clock": {
            "limit": 180,
            "increment": 0
        },
        "rated": true,
        "fullName": "Daily King of the Hill Arena",
        "nbPlayers": 0,
        "variant": {
            "key": "kingOfTheHill",
            "short": "KotH",
            "name": "King of the Hill"
        },
        "startsAt": 1781211640000,
        "finishesAt": 1781215240000,
        "status": 10,
        "perf": {
            "key": "kingOfTheHill",
            "name": "King of the Hill",
            "position": 7
        },
        "secondsToStart": 19011,
        "minRatedGames": {
            "nb": 15
        },
        "schedule": {
            "freq": "daily",
            "speed": "superBlitz"
        }
    },
    {
        "id": "nXkKqgZF",
        "createdBy": "lichess",
        "system": "arena",
        "minutes": 27,
        "clock": {
            "limit": 60,
            "increment": 1
        },
        "rated": true,
        "fullName": "≤1500 Bullet Arena",
        "nbPlayers": 0,
        "variant": {
            "key": "standard",
            "short": "Std",
            "name": "Standard"
        },
        "startsAt": 1781213400000,
        "finishesAt": 1781215020000,
        "status": 10,
        "perf": {
            "key": "bullet",
            "name": "Bullet",
            "position": 0,
            "icon": "T"
        },
        "secondsToStart": 20771,
        "hasMaxRating": true,
        "maxRating": {
            "rating": 1500
        },
        "minRatedGames": {
            "nb": 20
        },
        "schedule": {
            "freq": "hourly",
            "speed": "bullet"
        }
    },
    {
        "id": "xK6dtZ77",
        "createdBy": "lichess",
        "system": "arena",
        "minutes": 27,
        "clock": {
            "limit": 60,
            "increment": 0
        },
        "rated": true,
        "fullName": "Hourly Three-check Arena",
        "nbPlayers": 0,
        "variant": {
            "key": "threeCheck",
            "short": "3check",
            "name": "Three-check"
        },
        "startsAt": 1781213410000,
        "finishesAt": 1781215030000,
        "status": 10,
        "perf": {
            "key": "threeCheck",
            "name": "Three-Check",
            "position": 8
        },
        "secondsToStart": 20781,
        "schedule": {
            "freq": "hourly",
            "speed": "bullet"
        }
    },
    {
        "id": "gUwP3wSX",
        "createdBy": "lichess",
        "system": "arena",
        "minutes": 27,
        "clock": {
            "limit": 0,
            "increment": 2
        },
        "rated": true,
        "fullName": "Hourly Antichess Arena",
        "nbPlayers": 0,
        "variant": {
            "key": "antichess",
            "short": "Anti",
            "name": "Antichess"
        },
        "startsAt": 1781213420000,
        "finishesAt": 1781215040000,
        "status": 10,
        "perf": {
            "key": "antichess",
            "name": "Antichess",
            "position": 9
        },
        "secondsToStart": 20791,
        "schedule": {
            "freq": "hourly",
            "speed": "bullet"
        }
    },
    {
        "id": "ImqnLccW",
        "createdBy": "lichess",
        "system": "arena",
        "minutes": 27,
        "clock": {
            "limit": 60,
            "increment": 0
        },
        "rated": true,
        "fullName": "Hourly Bullet Arena",
        "nbPlayers": 0,
        "variant": {
            "key": "standard",
            "short": "Std",
            "name": "Standard"
        },
        "startsAt": 1781213440000,
        "finishesAt": 1781215060000,
        "status": 10,
        "perf": {
            "key": "bullet",
            "name": "Bullet",
            "position": 0,
            "icon": "T"
        },
        "secondsToStart": 20811,
        "minRatedGames": {
            "nb": 20
        },
        "schedule": {
            "freq": "hourly",
            "speed": "bullet"
        }
    }
]